lexicon/__init__.py
lexicon/_version.py
lexicon/alias_dict.py
lexicon/attribute_dict.py
lexicon-2.0.1.dist-info/LICENSE
lexicon-2.0.1.dist-info/METADATA
lexicon-2.0.1.dist-info/WHEEL
lexicon-2.0.1.dist-info/top_level.txt
lexicon-2.0.1.dist-info/RECORD
