Metadata-Version: 2.1
Name: lexicon
Version: 2.0.1
Summary: Powerful dict subclass(es) with aliasing & attribute access
Home-page: https://github.com/bitprophet/lexicon#what
Author: Jeff Forcier
Author-email: jeff@bitprophet.org
License: BSD
Project-URL: Source, https://github.com/bitprophet/lexicon
Project-URL: Changelog, https://github.com/bitprophet/lexicon/blob/main/docs/changelog.rst
Project-URL: CI, https://app.circleci.com/pipelines/github/bitprophet/lexicon
Platform: UNKNOWN
Classifier: Development Status :: 5 - Production/Stable
Classifier: Environment :: Console
Classifier: Intended Audience :: Developers
Classifier: License :: OSI Approved :: BSD License
Classifier: Operating System :: MacOS :: MacOS X
Classifier: Operating System :: Unix
Classifier: Operating System :: POSIX
Classifier: Programming Language :: Python
Classifier: Programming Language :: Python :: 3
Classifier: Programming Language :: Python :: 3.6
Classifier: Programming Language :: Python :: 3.7
Classifier: Programming Language :: Python :: 3.8
Classifier: Programming Language :: Python :: 3.9
Classifier: Topic :: Software Development
Classifier: Topic :: Software Development :: Libraries
Classifier: Topic :: Software Development :: Libraries :: Python Modules
